quick_access
