Metadata-Version: 2.1
Name: quick-access
Version: 1.1.2
Summary: Quick and easy python functions for all purposes.
Author: MITdude
Keywords: python,easy,python quick,quick access
Classifier: Development Status :: 3 - Alpha
Classifier: Intended Audience :: Developers
Classifier: Programming Language :: Python :: 2
Classifier: Programming Language :: Python :: 3
